LICENSE
MANIFEST.in
README.md
requirements.txt
setup.cfg
setup.py
Carpenter.egg-info/PKG-INFO
Carpenter.egg-info/SOURCES.txt
Carpenter.egg-info/dependency_links.txt
Carpenter.egg-info/not-zip-safe
Carpenter.egg-info/requires.txt
Carpenter.egg-info/top_level.txt
carpenter/__init__.py
carpenter/carpenter.py
carpenter/blocks/__init__.py
carpenter/blocks/block.py
carpenter/blocks/cellanalyzer.py
carpenter/blocks/flagable.py
carpenter/blocks/parentpath.py
carpenter/blocks/tableanalyzer.py
carpenter/regex/__init__.py
carpenter/regex/allregex.py
carpenter/regex/data.py
carpenter/regex/date.py
carpenter/regex/extendedtypes.py
carpenter/regex/location.py
carpenter/regex/titles.py
carpenter/regex/types.py
tests/__init__.py
tests/analyzer_test.py
tests/carpenter_test.py
tests/parentpath.py
tests/regex_types_test.py