Metadata-Version: 1.1
Name: Carpenter
Version: 1.0.0
Summary: A utility library which repairs and analyzes tablular data
Home-page: https://github.com/OpenGov/carpenter
Author: Matthew Seal
Author-email: mseal@opengov.us
License: LGPL 2.1
Download-URL: https://github.com/OpenGov/carpenter/tarball/v1.0.0
Keywords: tables,data,analysis,extraction
Platform: UNKNOWN
Classifier: Development Status :: 3 - Alpha
Classifier: Topic :: Utilities
Classifier: License :: OSI Approved :: GNU Lesser General Public License v2 (LGPLv2)
Classifier: Natural Language :: English
Classifier: Programming Language :: Python :: 2 :: Only
